pyvizml/__init__.py
pyvizml/pyvizml.py
pyvizml-1.0.2.dist-info/LICENSE
pyvizml-1.0.2.dist-info/METADATA
pyvizml-1.0.2.dist-info/WHEEL
pyvizml-1.0.2.dist-info/top_level.txt
pyvizml-1.0.2.dist-info/RECORD
