Metadata-Version: 2.1
Name: pyvizml
Version: 1.0.2
Summary: A package for my book: Machine Learning for Newbies.
Home-page: https://yaojenkuo.io/ml-newbies/index.html
Author: Kuo, Yao-Jen
Author-email: tonykuoyj@gmail.com
License: UNKNOWN
Platform: UNKNOWN
Classifier: Programming Language :: Python :: 3
Classifier: License :: OSI Approved :: MIT License
Classifier: Operating System :: OS Independent
Requires-Python: >=3.6
Requires-Dist: requests
Requires-Dist: numpy
Requires-Dist: pandas (>=1)
Requires-Dist: matplotlib
Requires-Dist: tqdm
